{
  "cli": {
    "version": ">= 15.0.0"
  },
  "build": {
    "development": {
      "developmentClient": true,
      "distribution": "internal",
      "android": {
        "buildType": "apk"
      }
    },
    "preview": {
      "distribution": "internal",
      "android": {
        "buildType": "apk"
      }
    },
    "production": {
      "distribution": "store",
      "autoIncrement": true,
      "env": {
        "EXPO_PUBLIC_CLERK_PUBLISHABLE_KEY": "${EXPO_PUBLIC_CLERK_PUBLISHABLE_KEY}",
        "EXPO_PUBLIC_API_URL": "https://rhynode-finance.vercel.app",
        "EXPO_PUBLIC_SENTRY_DSN": "${EXPO_PUBLIC_SENTRY_DSN}",
        "EXPO_PUBLIC_POSTHOG_KEY": "${EXPO_PUBLIC_POSTHOG_KEY}",
        "EXPO_PUBLIC_POSTHOG_HOST": "${EXPO_PUBLIC_POSTHOG_HOST}"
      },
      "android": {
        "buildType": "app-bundle"
      },
      "ios": {
        "buildConfiguration": "Release"
      }
    }
  },
  "submit": {
    "production": {
      "android": {
        "track": "internal"
      }
    }
  }
}
